iflow_mcp_jenkins_mcp-0.1.1.dist-info/licenses/LICENSE
jenkins_mcp/__init__.py
jenkins_mcp/server.py
iflow_mcp_jenkins_mcp-0.1.1.dist-info/METADATA
iflow_mcp_jenkins_mcp-0.1.1.dist-info/WHEEL
iflow_mcp_jenkins_mcp-0.1.1.dist-info/entry_points.txt
iflow_mcp_jenkins_mcp-0.1.1.dist-info/top_level.txt
iflow_mcp_jenkins_mcp-0.1.1.dist-info/RECORD
