Metadata-Version: 2.4
Name: iflow-mcp_jenkins-mcp
Version: 0.1.1
Summary: MCP server for managing Jenkins operations
Author: Kristof Jozsa
Project-URL: Repository, https://github.com/kjozsa/jenkins-mcp
Requires-Python: >=3.10
License-File: LICENSE
Requires-Dist: fastmcp
Requires-Dist: python-jenkins
Requires-Dist: loguru
Requires-Dist: requests
Dynamic: license-file
